setup.py
pyservant.egg-info/PKG-INFO
pyservant.egg-info/SOURCES.txt
pyservant.egg-info/dependency_links.txt
pyservant.egg-info/requires.txt
pyservant.egg-info/top_level.txt
servant/__init__.py
servant/config.py
servant/constants.py
servant/exceptions.py
servant/fields.py
servant/logger.py
servant/serializers.py
servant/utils.py
servant/client/__init__.py
servant/client/foo.py
servant/client/response.py
servant/service/__init__.py
servant/service/base.py
servant/service/response.py
servant/service/actions/__init__.py
servant/service/actions/base.py
servant/service/actions/mixins.py
servant/service/actions/stdactions.py
servant/transport/__init__.py
servant/transport/base.py
servant/transport/http.py
servant/transport/local.py