Metadata-Version: 1.1
Name: pyservant
Version: 0.0.9
Summary: A library for building services
Home-page: https://github.com/brianz/servant
Author: Brian Zambrano
Author-email: brianz@gmail.com
License: UNKNOWN
Platform: UNKNOWN
Classifier: Programming Language :: Python
Classifier: Programming Language :: Python :: 2
Classifier: License :: OSI Approved :: GNU Lesser General Public License v3 (LGPLv3)
Classifier: Operating System :: OS Independent
Classifier: Development Status :: 4 - Beta
Classifier: Environment :: Console
Classifier: Intended Audience :: Developers
Classifier: Topic :: System :: Distributed Computing
